flask_bp_autoregister/__init__.py
flask_bp_autoregister/blueprints.py
flask_bp_autoregister/tests.py
autoinclude_blueprints-1.0.1.dist-info/LICENSE.md
autoinclude_blueprints-1.0.1.dist-info/METADATA
autoinclude_blueprints-1.0.1.dist-info/WHEEL
autoinclude_blueprints-1.0.1.dist-info/top_level.txt
autoinclude_blueprints-1.0.1.dist-info/RECORD
