Metadata-Version: 2.1
Name: autoinclude-blueprints
Version: 1.0.1
Summary: Auto register all project flask-blueprints.
Home-page: https://github.com/FelixTheC/flask_bp_autoregister
Author: FelixTheC
Author-email: fberndt87@gmail.com
License: MIT
Platform: UNKNOWN
Classifier: License :: OSI Approved :: MIT License
Classifier: Programming Language :: Python :: 3
Requires-Python: >=3.6
Requires-Dist: flask (>=1.1.0)
Requires-Dist: strongtyping (>=1.3.0)
